agents_config/__init__.py
agents_config/agent_config.py
agents_config/ai_config.py
agents_config/base.py
agents_config/config_loader.py
agents_config/config_models.py
agents_config/model_config.py
agents_config/tool_config.py
agents_config-0.2.0.dist-info/licenses/LICENSE
ai-config/ai-config.yaml
ai-config/prompts/combined-search-agent.prompt.md
ai-config/prompts/opoint-agent.prompt.md
ai-config/prompts/search-agent.prompt.md
ai-config/tools/ai_foundry/opoint.schema.json
ai-config/tools/openapi/opoint.schema.json
agents_config-0.2.0.dist-info/METADATA
agents_config-0.2.0.dist-info/WHEEL
agents_config-0.2.0.dist-info/top_level.txt
agents_config-0.2.0.dist-info/RECORD
