Metadata-Version: 2.4
Name: agents-config
Version: 0.2.0
Summary: Robust Pydantic models for AI agent configuration with environment variable substitution
Author-email: kdcllc <info@kingdavidconsulting.com>
Maintainer-email: kdcllc <info@kingdavidconsulting.com>
License-Expression: MIT
Project-URL: Homepage, https://github.com/kdcllc/agents_config
Project-URL: Documentation, https://github.com/kdcllc/agents_config#readme
Project-URL: Repository, https://github.com/kdcllc/agents_config.git
Project-URL: Bug Tracker, https://github.com/kdcllc/agents_config/issues
Keywords: ai,agents,configuration,pydantic,yaml
Classifier: Development Status :: 4 - Beta
Classifier: Intended Audience :: Developers
Classifier: Operating System :: OS Independent
Classifier: Programming Language :: Python :: 3
Classifier: Programming Language :: Python :: 3.12
Classifier: Programming Language :: Python :: 3.13
Classifier: Topic :: Software Development :: Libraries :: Python Modules
Classifier: Topic :: Scientific/Engineering :: Artificial Intelligence
Requires-Python: >=3.12
License-File: LICENSE
Requires-Dist: pydantic>=2.0.0
Requires-Dist: PyYAML>=6.0.0
Requires-Dist: typing-extensions>=4.0.0
Provides-Extra: dev
Requires-Dist: pytest>=7.0.0; extra == "dev"
Requires-Dist: pytest-cov>=4.0.0; extra == "dev"
Requires-Dist: black>=23.0.0; extra == "dev"
Requires-Dist: isort>=5.0.0; extra == "dev"
Requires-Dist: flake8>=6.0.0; extra == "dev"
Requires-Dist: mypy>=1.0.0; extra == "dev"
Requires-Dist: types-PyYAML>=6.0.0; extra == "dev"
Dynamic: license-file
